{
  "https://console.spec.whatwg.org/": 202,
  "https://dom.spec.whatwg.org/": 5,
  "https://drafts.css-houdini.org/css-paint-api/": null,
  "https://drafts.css-houdini.org/css-properties-values-api/": null,
  "https://drafts.css-houdini.org/css-typed-om/": null,
  "https://drafts.csswg.org/css-align/": 58,
  "https://drafts.csswg.org/css-animations-2/": 31,
  "https://drafts.csswg.org/css-animations/": 156,
  "https://drafts.csswg.org/css-backgrounds-4/": 122,
  "https://drafts.csswg.org/css-backgrounds/": 117,
  "https://drafts.csswg.org/css-box-4/": 170,
  "https://drafts.csswg.org/css-box/": 170,
  "https://drafts.csswg.org/css-break/": 678,
  "https://drafts.csswg.org/css-cascade-5/": 678,
  "https://drafts.csswg.org/css-cascade/": 33,
  "https://drafts.csswg.org/css-color-5/": 2,
  "https://drafts.csswg.org/css-color-6/": 124,
  "https://drafts.csswg.org/css-color-adjust/": 60,
  "https://drafts.csswg.org/css-color/": 2,
  "https://drafts.csswg.org/css-conditional-3/": 159,
  "https://drafts.csswg.org/css-conditional-4/": 474,
  "https://drafts.csswg.org/css-contain/": 57,
  "https://drafts.csswg.org/css-content/": 415,
  "https://drafts.csswg.org/css-counter-styles/": 117,
  "https://drafts.csswg.org/css-display/": 58,
  "https://drafts.csswg.org/css-easing/": 65,
  "https://drafts.csswg.org/css-env/": 68,
  "https://drafts.csswg.org/css-flexbox/": 8,
  "https://drafts.csswg.org/css-font-loading/": 421,
  "https://drafts.csswg.org/css-fonts-5/": 174,
  "https://drafts.csswg.org/css-fonts/": 33,
  "https://drafts.csswg.org/css-grid-3/": 135,
  "https://drafts.csswg.org/css-grid/": 86,
  "https://drafts.csswg.org/css-images-4/": 33,
  "https://drafts.csswg.org/css-images/": 110,
  "https://drafts.csswg.org/css-inline/": 100,
  "https://drafts.csswg.org/css-lists/": 23,
  "https://drafts.csswg.org/css-logical/": 529,
  "https://drafts.csswg.org/css-multicol/": 226,
  "https://drafts.csswg.org/css-namespaces/": 254,
  "https://drafts.csswg.org/css-overflow/": 108,
  "https://drafts.csswg.org/css-overscroll/": 856,
  "https://drafts.csswg.org/css-page/": 124,
  "https://drafts.csswg.org/css-position/": 118,
  "https://drafts.csswg.org/css-pseudo/": 9,
  "https://drafts.csswg.org/css-rhythm/": 205,
  "https://drafts.csswg.org/css-ruby/": 356,
  "https://drafts.csswg.org/css-scoping/": 58,
  "https://drafts.csswg.org/css-scroll-anchoring/": 20,
  "https://drafts.csswg.org/css-scroll-snap/": 166,
  "https://drafts.csswg.org/css-scrollbars/": 296,
  "https://drafts.csswg.org/css-shadow-parts/": 122,
  "https://drafts.csswg.org/css-shapes/": 25,
  "https://drafts.csswg.org/css-size-adjust/": 529,
  "https://drafts.csswg.org/css-sizing-4/": 100,
  "https://drafts.csswg.org/css-sizing/": 346,
  "https://drafts.csswg.org/css-text-4/": 30,
  "https://drafts.csswg.org/css-text-decor-4/": 170,
  "https://drafts.csswg.org/css-text-decor/": 529,
  "https://drafts.csswg.org/css-text/": 104,
  "https://drafts.csswg.org/css-transforms-2/": 459,
  "https://drafts.csswg.org/css-transforms/": 31,
  "https://drafts.csswg.org/css-transitions-2/": 159,
  "https://drafts.csswg.org/css-transitions/": 9,
  "https://drafts.csswg.org/css-ui/": 10,
  "https://drafts.csswg.org/css-values-5/": 10,
  "https://drafts.csswg.org/css-values/": 31,
  "https://drafts.csswg.org/css-variables/": 62,
  "https://drafts.csswg.org/css-will-change/": 1164,
  "https://drafts.csswg.org/css-writing-modes/": 104,
  "https://drafts.csswg.org/css2/": 143,
  "https://drafts.csswg.org/cssom-view/": 2,
  "https://drafts.csswg.org/cssom/": 16,
  "https://drafts.csswg.org/mediaqueries-5/": 20,
  "https://drafts.csswg.org/mediaqueries/": 529,
  "https://drafts.csswg.org/resize-observer/": 891,
  "https://drafts.csswg.org/scroll-animations/": 103,
  "https://drafts.csswg.org/selectors/": 61,
  "https://drafts.csswg.org/web-animations-1/": 119,
  "https://drafts.csswg.org/web-animations-2/": 41,
  "https://drafts.fxtf.org/compositing/": 1277,
  "https://drafts.fxtf.org/css-masking/": null,
  "https://drafts.fxtf.org/filter-effects-2/": null,
  "https://drafts.fxtf.org/filter-effects/": null,
  "https://drafts.fxtf.org/geometry/": null,
  "https://drafts.fxtf.org/motion/": null,
  "https://encoding.spec.whatwg.org/": 20,
  "https://fetch.spec.whatwg.org/": 20,
  "https://fs.spec.whatwg.org/": 373,
  "https://fullscreen.spec.whatwg.org/": 145,
  "https://gpuweb.github.io/gpuweb/": 3,
  "https://html.spec.whatwg.org/multipage/": 0,
  "https://httpwg.org/http-extensions/draft-ietf-httpbis-rfc6265bis.html": 1,
  "https://httpwg.org/specs/rfc6265.html": 132,
  "https://httpwg.org/specs/rfc6266.html": 132,
  "https://httpwg.org/specs/rfc7838.html": 132,
  "https://httpwg.org/specs/rfc8246.html": 132,
  "https://httpwg.org/specs/rfc9110.html": 132,
  "https://httpwg.org/specs/rfc9111.html": 132,
  "https://httpwg.org/specs/rfc9112.html": 132,
  "https://httpwg.org/specs/rfc9113.html": 132,
  "https://immersive-web.github.io/anchors/": 849,
  "https://immersive-web.github.io/depth-sensing/": 46,
  "https://immersive-web.github.io/dom-overlays/": 285,
  "https://immersive-web.github.io/hit-test/": 390,
  "https://immersive-web.github.io/layers/": 93,
  "https://immersive-web.github.io/lighting-estimation/": 1129,
  "https://immersive-web.github.io/webxr-ar-module/": 72,
  "https://immersive-web.github.io/webxr-gamepads-module/": 453,
  "https://immersive-web.github.io/webxr-hand-input/": 396,
  "https://immersive-web.github.io/webxr/": 80,
  "https://notifications.spec.whatwg.org/": 167,
  "https://privacycg.github.io/storage-access/": 86,
  "https://registry.khronos.org/webgl/specs/latest/1.0/": 47,
  "https://registry.khronos.org/webgl/specs/latest/2.0/": 149,
  "https://sourcemaps.info/spec.html": 823,
  "https://storage.spec.whatwg.org/": 102,
  "https://streams.spec.whatwg.org/": 94,
  "https://svgwg.org/specs/animations/": 851,
  "https://svgwg.org/svg2-draft/": 851,
  "https://tc39.es/ecma262/multipage/": 6,
  "https://tc39.es/ecma402/": 23,
  "https://tc39.es/proposal-array-grouping/": 705,
  "https://tc39.es/proposal-atomics-wait-async/": 1558,
  "https://tc39.es/proposal-intl-enumeration/": 977,
  "https://tc39.es/proposal-intl-locale-info/": 24,
  "https://tc39.es/proposal-intl-numberformat-v3/out/numberformat/proposed.html": 728,
  "https://tc39.es/proposal-intl-numberformat-v3/out/pluralrules/proposed.html": 728,
  "https://url.spec.whatwg.org/": 55,
  "https://w3c.github.io/DOM-Parsing/": 128,
  "https://w3c.github.io/FileAPI/": 214,
  "https://w3c.github.io/IndexedDB/": 3,
  "https://w3c.github.io/IntersectionObserver/": 374,
  "https://w3c.github.io/ServiceWorker/": 18,
  "https://w3c.github.io/accelerometer/": 144,
  "https://w3c.github.io/ambient-light/": 144,
  "https://w3c.github.io/aria/": 9,
  "https://w3c.github.io/badging/": 796,
  "https://w3c.github.io/battery/": 255,
  "https://w3c.github.io/beacon/": 143,
  "https://w3c.github.io/clipboard-apis/": 51,
  "https://w3c.github.io/contact-api/spec/": 97,
  "https://w3c.github.io/deviceorientation/": 144,
  "https://w3c.github.io/encrypted-media/": 93,
  "https://w3c.github.io/event-timing/": 41,
  "https://w3c.github.io/gamepad/": 24,
  "https://w3c.github.io/gamepad/extensions.html": 24,
  "https://w3c.github.io/geolocation-api/": 97,
  "https://w3c.github.io/gyroscope/": 271,
  "https://w3c.github.io/hr-time/": 241,
  "https://w3c.github.io/html-media-capture/": 548,
  "https://w3c.github.io/input-events/": 261,
  "https://w3c.github.io/largest-contentful-paint/": 60,
  "https://w3c.github.io/longtasks/": 408,
  "https://w3c.github.io/magnetometer/": 144,
  "https://w3c.github.io/manifest-app-info/": 685,
  "https://w3c.github.io/manifest/": 62,
  "https://w3c.github.io/mathml-core/": 12,
  "https://w3c.github.io/media-capabilities/": 13,
  "https://w3c.github.io/media-playback-quality/": 367,
  "https://w3c.github.io/media-source/": 80,
  "https://w3c.github.io/mediacapture-fromelement/": 144,
  "https://w3c.github.io/mediacapture-image/": 74,
  "https://w3c.github.io/mediacapture-main/": 12,
  "https://w3c.github.io/mediacapture-output/": 80,
  "https://w3c.github.io/mediacapture-record/": 80,
  "https://w3c.github.io/mediacapture-screen-share/": 45,
  "https://w3c.github.io/mediacapture-transform/": 94,
  "https://w3c.github.io/mediasession/": 67,
  "https://w3c.github.io/navigation-timing/": 144,
  "https://w3c.github.io/network-error-logging/": 62,
  "https://w3c.github.io/orientation-sensor/": 543,
  "https://w3c.github.io/paint-timing/": 50,
  "https://w3c.github.io/payment-handler/": 893,
  "https://w3c.github.io/payment-request/": 95,
  "https://w3c.github.io/performance-timeline/": 46,
  "https://w3c.github.io/permissions/": 12,
  "https://w3c.github.io/picture-in-picture/": 202,
  "https://w3c.github.io/pointerevents/": 66,
  "https://w3c.github.io/pointerlock/": 384,
  "https://w3c.github.io/presentation-api/": 144,
  "https://w3c.github.io/push-api/": 223,
  "https://w3c.github.io/remote-playback/": 432,
  "https://w3c.github.io/reporting/": 25,
  "https://w3c.github.io/requestidlecallback/": 46,
  "https://w3c.github.io/resource-timing/": 33,
  "https://w3c.github.io/screen-orientation/": 697,
  "https://w3c.github.io/screen-wake-lock/": 255,
  "https://w3c.github.io/selection-api/": 182,
  "https://w3c.github.io/sensors/": 500,
  "https://w3c.github.io/server-timing/": 144,
  "https://w3c.github.io/touch-events/": 365,
  "https://w3c.github.io/trusted-types/dist/spec/": 3,
  "https://w3c.github.io/uievents/": 303,
  "https://w3c.github.io/user-timing/": 144,
  "https://w3c.github.io/vibration/": 144,
  "https://w3c.github.io/web-locks/": 65,
  "https://w3c.github.io/web-share/": 395,
  "https://w3c.github.io/webappsec-clear-site-data/": 604,
  "https://w3c.github.io/webappsec-credential-management/": 327,
  "https://w3c.github.io/webappsec-csp/": 6,
  "https://w3c.github.io/webappsec-cspee/": 669,
  "https://w3c.github.io/webappsec-fetch-metadata/": 96,
  "https://w3c.github.io/webappsec-permissions-policy/": 61,
  "https://w3c.github.io/webappsec-referrer-policy/": 247,
  "https://w3c.github.io/webappsec-subresource-integrity/": 0,
  "https://w3c.github.io/webappsec-upgrade-insecure-requests/": 997,
  "https://w3c.github.io/webauthn/": 18,
  "https://w3c.github.io/webcodecs/": 27,
  "https://w3c.github.io/webcrypto/": 3,
  "https://w3c.github.io/webdriver/": 5,
  "https://w3c.github.io/webrtc-extensions/": 24,
  "https://w3c.github.io/webrtc-identity/": 572,
  "https://w3c.github.io/webrtc-pc/": 20,
  "https://w3c.github.io/webrtc-stats/": 100,
  "https://w3c.github.io/webvtt/": 114,
  "https://w3c.github.io/woff/woff2/": 328,
  "https://webassembly.github.io/exception-handling/js-api/": 108,
  "https://webassembly.github.io/spec/js-api/": 12,
  "https://webassembly.github.io/spec/web-api/": 12,
  "https://webaudio.github.io/web-audio-api/": 97,
  "https://webaudio.github.io/web-midi-api/": 166,
  "https://webbluetoothcg.github.io/web-bluetooth/": 11,
  "https://websockets.spec.whatwg.org/": 529,
  "https://wicg.github.io/background-fetch/": 1537,
  "https://wicg.github.io/background-sync/spec/": 1332,
  "https://wicg.github.io/compression/": 13,
  "https://wicg.github.io/content-index/spec/": 1545,
  "https://wicg.github.io/controls-list/": 507,
  "https://wicg.github.io/cookie-store/": 4,
  "https://wicg.github.io/deprecation-reporting/": 1742,
  "https://wicg.github.io/element-timing/": 13,
  "https://wicg.github.io/entries-api/": 152,
  "https://wicg.github.io/eyedropper-api/": 1194,
  "https://wicg.github.io/file-system-access/": 111,
  "https://wicg.github.io/idle-detection/": 180,
  "https://wicg.github.io/input-device-capabilities/": 1581,
  "https://wicg.github.io/intervention-reporting/": 1948,
  "https://wicg.github.io/keyboard-lock/": 1369,
  "https://wicg.github.io/keyboard-map/": 1115,
  "https://wicg.github.io/layout-instability/": 1294,
  "https://wicg.github.io/manifest-incubations/": 37,
  "https://wicg.github.io/netinfo/": 1882,
  "https://wicg.github.io/periodic-background-sync/": 1546,
  "https://wicg.github.io/priority-hints/": 865,
  "https://wicg.github.io/sanitizer-api/": 4,
  "https://wicg.github.io/savedata/": 885,
  "https://wicg.github.io/scheduling-apis/": 37,
  "https://wicg.github.io/serial/": 75,
  "https://wicg.github.io/shape-detection-api/": 180,
  "https://wicg.github.io/speech-api/": 13,
  "https://wicg.github.io/ua-client-hints/": 58,
  "https://wicg.github.io/urlpattern/": 13,
  "https://wicg.github.io/web-otp/": 152,
  "https://wicg.github.io/webhid/": 296,
  "https://wicg.github.io/webusb/": 143,
  "https://wicg.github.io/window-controls-overlay/": 767,
  "https://www.rfc-editor.org/rfc/rfc2397": 6,
  "https://www.rfc-editor.org/rfc/rfc6797": 6,
  "https://www.rfc-editor.org/rfc/rfc7578": 6,
  "https://www.rfc-editor.org/rfc/rfc8942": 6,
  "https://xhr.spec.whatwg.org/": 118
}
